mlmodels/__init__.py
mlmodels/registermodels.py
registermlmodels-0.1.dist-info/LICENSE
registermlmodels-0.1.dist-info/METADATA
registermlmodels-0.1.dist-info/WHEEL
registermlmodels-0.1.dist-info/top_level.txt
registermlmodels-0.1.dist-info/RECORD
