Metadata-Version: 2.1
Name: registermlmodels
Version: 0.1
Summary: Register ML Models in Databricks
Home-page: https://github.com/v1pankaj/register-databricks-ml-models
Author: Pankaj Verma
Author-email: pankaj065@gmail.com
License: MIT
Platform: UNKNOWN
Requires-Dist: mlflow
